ddprimer/__init__.py
ddprimer/main.py
ddprimer/config/__init__.py
ddprimer/config/config.py
ddprimer/config/config_display.py
ddprimer/config/exceptions.py
ddprimer/config/logging_config.py
ddprimer/config/template_generator.py
ddprimer/core/__init__.py
ddprimer/core/annotation_processor.py
ddprimer/core/blast_processor.py
ddprimer/core/filter_processor.py
ddprimer/core/primer3_processor.py
ddprimer/core/primer_processor.py
ddprimer/core/sequence_processor.py
ddprimer/core/snp_processor.py
ddprimer/core/thermo_processor.py
ddprimer/utils/__init__.py
ddprimer/utils/blast_db_manager.py
ddprimer/utils/direct_mode.py
ddprimer/utils/file_io.py
ddprimer/utils/file_preparator.py
ddprimer/utils/primer_remapper.py
ddprimer-0.1.1.dist-info/licenses/LICENSE
ddprimer-0.1.1.dist-info/METADATA
ddprimer-0.1.1.dist-info/WHEEL
ddprimer-0.1.1.dist-info/entry_points.txt
ddprimer-0.1.1.dist-info/top_level.txt
ddprimer-0.1.1.dist-info/RECORD
