Metadata-Version: 2.4
Name: ddprimer
Version: 0.1.1
Summary: A pipeline for designing primers optimized for droplet digital PCR
Author-email: Jakob Wimmer <globuds133@gmail.com>
License-Expression: MIT
Project-URL: Homepage, https://github.com/globuzzz2000/ddPrimer
Project-URL: Documentation, https://github.com/globuzzz2000/ddPrimer#readme
Project-URL: Bug Tracker, https://github.com/globuzzz2000/ddPrimer/issues
Project-URL: Repository, https://github.com/globuzzz2000/ddPrimer.git
Classifier: Development Status :: 4 - Beta
Classifier: Intended Audience :: Science/Research
Classifier: Topic :: Scientific/Engineering :: Bio-Informatics
Classifier: Programming Language :: Python :: 3
Classifier: Programming Language :: Python :: 3 :: Only
Classifier: Programming Language :: Python :: 3.10
Classifier: Programming Language :: Python :: 3.11
Classifier: Programming Language :: Python :: 3.12
Requires-Python: >=3.10
License-File: LICENSE
Requires-Dist: biopython>=1.78
Requires-Dist: pandas>=1.3.0
Requires-Dist: numpy>=1.20.0
Requires-Dist: tqdm>=4.60.0
Requires-Dist: primer3-py>=2.0.0
Requires-Dist: openpyxl>=3.0.5
Requires-Dist: wxpython>=4.1.0
Requires-Dist: viennarna>=2.7.0
Requires-Dist: colorama>=0.4.4
Requires-Dist: pyobjc-core>=8.0; platform_system == "Darwin"
Requires-Dist: pyobjc-framework-Cocoa>=8.0; platform_system == "Darwin"
Provides-Extra: dev
Requires-Dist: pytest>=7.0.0; extra == "dev"
Requires-Dist: pytest-cov>=4.0.0; extra == "dev"
Requires-Dist: black>=22.0.0; extra == "dev"
Requires-Dist: mock>=5.0.0; extra == "dev"
Requires-Dist: flake8>=5.0.0; extra == "dev"
Provides-Extra: test
Requires-Dist: pytest>=7.0.0; extra == "test"
Requires-Dist: pytest-cov>=4.0.0; extra == "test"
Requires-Dist: mock>=5.0.0; extra == "test"
Dynamic: license-file
